contour3d.py
contour3d-0.1.2.dist-info/DESCRIPTION.rst
contour3d-0.1.2.dist-info/METADATA
contour3d-0.1.2.dist-info/RECORD
contour3d-0.1.2.dist-info/WHEEL
contour3d-0.1.2.dist-info/entry_points.txt
contour3d-0.1.2.dist-info/metadata.json
contour3d-0.1.2.dist-info/top_level.txt
