Metadata-Version: 2.0
Name: contour3d
Version: 0.1.2
Summary: Contour 3D algorithm for grid data.
Home-page: https://github.com/vitroid/contour/
Author: Masakazu Matsumoto
Author-email: vitroid@gmail.com
License: MIT
Keywords: contour,3D
Platform: UNKNOWN
Classifier: Development Status :: 4 - Beta
Classifier: Intended Audience :: Developers
Classifier: Programming Language :: Python
Classifier: Programming Language :: Python :: 3.5
Requires-Dist: numpy
Requires-Dist: yaplotlib (>=0.1)
